{
    "Chambre - Pyramide": {
        "light_id": 1,
        "name": "Chambre - Pyramide",
        "on": true,
        "brightness": 254,
        "colormode": null,
        "hue": null,
        "saturation": null,
        "xy": null,
        "colortemp": null,
        "effect": null,
        "alert": "select",
        "transitiontime": null,
        "reset_bri_after_on": null,
        "reachable": false,
        "type": "Dimmable light"
    },
    "Salon Petit Lampadaire": {
        "light_id": 3,
        "name": "Salon Petit Lampadaire",
        "on": false,
        "brightness": 254,
        "colormode": "ct",
        "hue": 8417,
        "saturation": 140,
        "xy": [
            0.4573,
            0.41
        ],
        "colortemp": 366,
        "effect": "none",
        "alert": "select",
        "transitiontime": null,
        "reset_bri_after_on": null,
        "reachable": true,
        "type": "Extended color light"
    },
    "Lampadaire Salle \u00e0 manger": {
        "light_id": 4,
        "name": "Lampadaire Salle \u00e0 manger",
        "on": false,
        "brightness": 254,
        "colormode": "ct",
        "hue": 8417,
        "saturation": 140,
        "xy": [
            0.4573,
            0.41
        ],
        "colortemp": 366,
        "effect": "none",
        "alert": "select",
        "transitiontime": null,
        "reset_bri_after_on": null,
        "reachable": true,
        "type": "Extended color light"
    },
    "Chevet Antoine": {
        "light_id": 5,
        "name": "Chevet Antoine",
        "on": true,
        "brightness": 254,
        "colormode": "ct",
        "hue": 8417,
        "saturation": 140,
        "xy": [
            0.4573,
            0.41
        ],
        "colortemp": 366,
        "effect": "none",
        "alert": "select",
        "transitiontime": null,
        "reset_bri_after_on": null,
        "reachable": false,
        "type": "Extended color light"
    },
    "Chevet Sil\u00e8ne": {
        "light_id": 6,
        "name": "Chevet Sil\u00e8ne",
        "on": true,
        "brightness": 254,
        "colormode": "ct",
        "hue": 8417,
        "saturation": 140,
        "xy": [
            0.4573,
            0.41
        ],
        "colortemp": 366,
        "effect": "none",
        "alert": "select",
        "transitiontime": null,
        "reset_bri_after_on": null,
        "reachable": false,
        "type": "Extended color light"
    },
    "Guirlande Chambre": {
        "light_id": 7,
        "name": "Guirlande Chambre",
        "on": true,
        "brightness": null,
        "colormode": null,
        "hue": null,
        "saturation": null,
        "xy": null,
        "colortemp": null,
        "effect": null,
        "alert": "select",
        "transitiontime": null,
        "reset_bri_after_on": null,
        "reachable": false,
        "type": "On/Off plug-in unit"
    },
    "Hue white spot 1": {
        "light_id": 8,
        "name": "Hue white spot 1",
        "on": false,
        "brightness": 0,
        "colormode": null,
        "hue": null,
        "saturation": null,
        "xy": null,
        "colortemp": null,
        "effect": null,
        "alert": "select",
        "transitiontime": null,
        "reset_bri_after_on": null,
        "reachable": false,
        "type": "Dimmable light"
    },
    "Hue white spot 2": {
        "light_id": 9,
        "name": "Hue white spot 2",
        "on": false,
        "brightness": 0,
        "colormode": null,
        "hue": null,
        "saturation": null,
        "xy": null,
        "colortemp": null,
        "effect": null,
        "alert": "select",
        "transitiontime": null,
        "reset_bri_after_on": null,
        "reachable": false,
        "type": "Dimmable light"
    },
    "Hue white spot 3": {
        "light_id": 10,
        "name": "Hue white spot 3",
        "on": false,
        "brightness": 0,
        "colormode": null,
        "hue": null,
        "saturation": null,
        "xy": null,
        "colortemp": null,
        "effect": null,
        "alert": "select",
        "transitiontime": null,
        "reset_bri_after_on": null,
        "reachable": false,
        "type": "Dimmable light"
    },
    "Hue white spot 4": {
        "light_id": 11,
        "name": "Hue white spot 4",
        "on": false,
        "brightness": 0,
        "colormode": null,
        "hue": null,
        "saturation": null,
        "xy": null,
        "colortemp": null,
        "effect": null,
        "alert": "select",
        "transitiontime": null,
        "reset_bri_after_on": null,
        "reachable": false,
        "type": "Dimmable light"
    }
}